pycolorkit/__init__.py
pycolorkit/color.py
pycolorkit-1.0.9.dist-info/METADATA
pycolorkit-1.0.9.dist-info/WHEEL
pycolorkit-1.0.9.dist-info/licenses/LICENSE
pycolorkit-1.0.9.dist-info/RECORD
