Metadata-Version: 2.3
Name: pycolorkit
Version: 1.0.9
Summary: A color conversion package
Project-URL: Homepage, https://github.com/codewithkate/pycolorkit
Project-URL: Issues, https://github.com/codewithkate/pycolorkit/issues
Author-email: Kaitlen Crawford <hello@codewithkate.com>
Classifier: License :: OSI Approved :: MIT License
Classifier: Operating System :: OS Independent
Classifier: Programming Language :: Python :: 3
Requires-Python: >=3.8
